Metadata-Version: 1.0
Name: dsnd-probability-yrmadev
Version: 0.1
Summary: Gaussian and Binomial distributions
Home-page: UNKNOWN
Author: Yrma Dev
Author-email: yrmadev@outlook.com
License: UNKNOWN
Platform: UNKNOWN
